solidview/__init__.py
solidview/viewer.py
solidview-0.1.0.dist-info/licenses/LICENSE
solidview-0.1.0.dist-info/METADATA
solidview-0.1.0.dist-info/WHEEL
solidview-0.1.0.dist-info/top_level.txt
solidview-0.1.0.dist-info/RECORD
