Metadata-Version: 2.4
Name: solidview
Version: 0.1.0
Summary: A Python package for 3D visualization of SolidPython2 objects
Home-page: https://github.com/Mr-KAM/solidview
Author: Anicet Cyrille KAMBOU
Author-email: Anicet Cyrille KAMBOU <kanicetcyrille@gmail.com>
License: MIT
Project-URL: Homepage, https://github.com/Mr-KAM/solidview
Project-URL: Documentation, https://mr-kam.github.io/solidview/
Project-URL: Repository, https://github.com/Mr-KAM/solidview
Project-URL: Bug Tracker, https://github.com/Mr-KAM/solidview/issues
Keywords: 3d,visualization,solidpython,openscad,jupyter,cad
Classifier: Development Status :: 3 - Alpha
Classifier: Intended Audience :: Developers
Classifier: Intended Audience :: Science/Research
Classifier: License :: OSI Approved :: MIT License
Classifier: Operating System :: OS Independent
Classifier: Programming Language :: Python :: 3
Classifier: Programming Language :: Python :: 3.8
Classifier: Programming Language :: Python :: 3.9
Classifier: Programming Language :: Python :: 3.10
Classifier: Programming Language :: Python :: 3.11
Classifier: Programming Language :: Python :: 3.12
Classifier: Topic :: Scientific/Engineering
Classifier: Topic :: Scientific/Engineering :: Visualization
Classifier: Topic :: Multimedia :: Graphics :: 3D Modeling
Requires-Python: >=3.8
License-File: LICENSE
Requires-Dist: solidpython2>=1.0.0
Requires-Dist: jupyterscad>=0.2.0
Requires-Dist: pathlib2; python_version < "3.4"
Provides-Extra: dev
Requires-Dist: pytest>=6.0; extra == "dev"
Requires-Dist: pytest-cov; extra == "dev"
Requires-Dist: black; extra == "dev"
Requires-Dist: isort; extra == "dev"
Requires-Dist: flake8; extra == "dev"
Requires-Dist: mypy; extra == "dev"
Provides-Extra: docs
Requires-Dist: sphinx; extra == "docs"
Requires-Dist: sphinx-rtd-theme; extra == "docs"
Dynamic: author
Dynamic: home-page
Dynamic: license-file
Dynamic: requires-python
